Design.v
`timescale 1ns / 1ps

module SISO(
   input din_i, 
   input clk_i, 
   output dout_o
);

//net(s)
wire D1;
wire D2;
wire D3;

//SISO Flip Flops
Dff B0(.D_i(din_i), 
   .clk_i(clk_i), 
   .dout_o(D1));
Dff B1(.D_i(D1), 
   .clk_i(clk_i), 
   .dout_o(D2));
Dff B2(.D_i(D2), 
   .clk_i(clk_i), 
   .dout_o(D3));
Dff B3(.D_i(D3), 
   .clk_i(clk_i), 
   .dout_o(dout_o));

endmodule

//D Flip Flop
module Dff(
   input D_i, 
   input clk_i, 
   output reg dout_o
);

always@(posedge clk_i)
   dout_o <= D_i;

endmodule

Testbench.v
`timescale 1ns / 1ps

module tb_SISO();
reg din_ti;
reg clk_ti;
wire dout_to;

//instantiation
SISO DUT(.din_i(din_ti), 
   .clk_i(clk_ti), 
   .dout_o(dout_to));

//clock
initial begin
   clk_ti = 1'b0;
   forever 
      #5 clk_ti = ~clk_ti;
end

//feeding
initial begin
   din_ti = 1'b0; 
   repeat(50)
      #10 din_ti = $urandom_range(0, 1);
   #10 $finish;
end

//capture
initial begin
$monitor("Time: %0t | Clock: %b | Input: %b | Output: %b", $time, clk_ti, din_ti, dout_to);
$dumpfile("SISO.vcd");
$dumpvars(0, tb_SISO);
end

endmodule

SISO.vcd
$date
   Sun Apr 26 14:29:52 2026
$end

$version
  2025.2
  $dumpfile ("SISO.vcd") 
$end

$timescale
  1ps
$end

$scope module tb_SISO $end
$var reg 1 ! din_ti $end
$var reg 1 " clk_ti $end
$var wire 1 # dout_to $end
$scope module DUT $end
$var wire 1 $ din_i $end
$var wire 1 % clk_i $end
$var wire 1 # dout_o $end
$var wire 1 & D1 $end
$var wire 1 ' D2 $end
$var wire 1 ( D3 $end
$scope module B0 $end
$var wire 1 $ D_i $end
$var wire 1 % clk_i $end
$var reg 1 ) dout_o $end
$upscope $end
$scope module B1 $end
$var wire 1 & D_i $end
$var wire 1 % clk_i $end
$var reg 1 * dout_o $end
$upscope $end
$scope module B2 $end
$var wire 1 ' D_i $end
$var wire 1 % clk_i $end
$var reg 1 + dout_o $end
$upscope $end
$scope module B3 $end
$var wire 1 ( D_i $end
$var wire 1 % clk_i $end
$var reg 1 , dout_o $end
$upscope $end
$upscope $end
$upscope $end
$enddefinitions $end

#0
$dumpvars
0!
0"
x#
0$
0%
x&
x'
x(
x)
x*
x+
x,
$end

#5000
1"
1%
0&
0)

#10000
1!
0"
1$
0%

#15000
1"
1%
1&
0'
1)
0*

#20000
0"
0%

#25000
1"
1%
1'
0(
1*
0+

#30000
0!
0"
0$
0%

#35000
1"
0#
1%
0&
1(
0)
1+
0,

#40000
0"
0%

#45000
1"
1#
1%
0'
0*
1,

#50000
1!
0"
1$
0%

#55000
1"
1%
1&
0(
1)
0+

#60000
0"
0%

#65000
1"
0#
1%
1'
1*
0,

#70000
0"
0%

#75000
1"
1%
1(
1+

#80000
0!
0"
0$
0%

#85000
1"
1#
1%
0&
0)
1,

#90000
1!
0"
1$
0%

#95000
1"
1%
1&
0'
1)
0*

#100000
0"
0%

#105000
1"
1%
1'
0(
1*
0+

#110000
0"
0%

#115000
1"
0#
1%
1(
1+
0,

#120000
0!
0"
0$
0%

#125000
1"
1#
1%
0&
0)
1,

#130000
0"
0%

#135000
1"
1%
0'
0*

#140000
0"
0%

#145000
1"
1%
0(
0+

#150000
0"
0%

#155000
1"
0#
1%
0,

#160000
1!
0"
1$
0%

#165000
1"
1%
1&
1)

#170000
0"
0%

#175000
1"
1%
1'
1*

#180000
0"
0%

#185000
1"
1%
1(
1+

#190000
0"
0%

#195000
1"
1#
1%
1,

#200000
0"
0%

#205000
1"
1%

#210000
0"
0%

#215000
1"
1%

#220000
0!
0"
0$
0%

#225000
1"
1%
0&
0)

#230000
1!
0"
1$
0%

#235000
1"
1%
1&
0'
1)
0*

#240000
0!
0"
0$
0%

#245000
1"
1%
0&
1'
0(
0)
1*
0+

#250000
1!
0"
1$
0%

#255000
1"
0#
1%
1&
0'
1(
1)
0*
1+
0,

#260000
0!
0"
0$
0%

#265000
1"
1#
1%
0&
1'
0(
0)
1*
0+
1,

#270000
0"
0%

#275000
1"
0#
1%
0'
1(
0*
1+
0,

#280000
1!
0"
1$
0%

#285000
1"
1#
1%
1&
0(
1)
0+
1,

#290000
0!
0"
0$
0%

#295000
1"
0#
1%
0&
1'
0)
1*
0,

#300000
1!
0"
1$
0%

#305000
1"
1%
1&
0'
1(
1)
0*
1+

#310000
0"
0%

#315000
1"
1#
1%
1'
0(
1*
0+
1,

#320000
0!
0"
0$
0%

#325000
1"
0#
1%
0&
1(
0)
1+
0,

#330000
1!
0"
1$
0%

#335000
1"
1#
1%
1&
0'
1)
0*
1,

#340000
0"
0%

#345000
1"
1%
1'
0(
1*
0+

#350000
0"
0%

#355000
1"
0#
1%
1(
1+
0,

#360000
0!
0"
0$
0%

#365000
1"
1#
1%
0&
0)
1,

#370000
0"
0%

#375000
1"
1%
0'
0*

#380000
0"
0%

#385000
1"
1%
0(
0+

#390000
0"
0%

#395000
1"
0#
1%
0,

#400000
0"
0%

#405000
1"
1%

#410000
0"
0%

#415000
1"
1%

#420000
1!
0"
1$
0%

#425000
1"
1%
1&
1)

#430000
0!
0"
0$
0%

#435000
1"
1%
0&
1'
0)
1*

#440000
0"
0%

#445000
1"
1%
0'
1(
0*
1+

#450000
1!
0"
1$
0%

#455000
1"
1#
1%
1&
0(
1)
0+
1,

#460000
0!
0"
0$
0%

#465000
1"
0#
1%
0&
1'
0)
1*
0,

#470000
0"
0%

#475000
1"
1%
0'
1(
0*
1+

#480000
1!
0"
1$
0%

#485000
1"
1#
1%
1&
0(
1)
0+
1,

#490000
0"
0%

#495000
1"
0#
1%
1'
1*
0,

#500000
0!
0"
0$
0%

#505000
1"
1%
0&
1(
0)
1+
